[
  {
    "id": "hrc-26-1",
    "name": "국가인권위원회법",
    "detail": "제26조(인권교육의 촉진)",
    "content": "위원회는 모든 사람의 인권의식을 깨우치고 향상시키기 위하여 필요한 인권교육과 홍보를 하여야 한다."
  },

  {
    "id": "edu-11",
    "name": "교육기본법",
    "detail": "제11조(인권존중)",
    "content": "교육은 인간의 존엄과 가치를 존중하여야 한다.교육은 인간의 존엄과 가치를 존중하여야 한다.교육은 인간의 존엄과 가치를 존중하여야 한다."
  },
  {
    "id": "hrc-26-1",
    "name": "국가인권위원회법",
    "detail": "제26조(인권교육의 촉진)",
    "content": "위원회는 모든 사람의 인권의식을 깨우치고 향상시키기 위하여 필요한 인권교육과 홍보를 하여야 한다."
  },

  {
    "id": "edu-11",
    "name": "교육기본법",
    "detail": "제11조(인권존중)",
    "content": "교육은 인간의 존엄과 가치를 존중하여야 한다.교육은 인간의 존엄과 가치를 존중하여야 한다.교육은 인간의 존엄과 가치를 존중하여야 한다."
  },
  {
    "id": "hrc-26-1",
    "name": "국가인권위원회법",
    "detail": "제26조(인권교육의 촉진)",
    "content": "위원회는 모든 사람의 인권의식을 깨우치고 향상시키기 위하여 필요한 인권교육과 홍보를 하여야 한다."
  },

  {
    "id": "edu-11",
    "name": "교육기본법",
    "detail": "제11조(인권존중)",
    "content": "교육은 인간의 존엄과 가치를 존중하여야 한다.교육은 인간의 존엄과 가치를 존중하여야 한다.교육은 인간의 존엄과 가치를 존중하여야 한다."
  },
  {
    "id": "hrc-26-1",
    "name": "국가인권위원회법",
    "detail": "제26조(인권교육의 촉진)",
    "content": "위원회는 모든 사람의 인권의식을 깨우치고 향상시키기 위하여 필요한 인권교육과 홍보를 하여야 한다."
  },

  {
    "id": "edu-11",
    "name": "교육기본법",
    "detail": "제11조(인권존중)",
    "content": "교육은 인간의 존엄과 가치를 존중하여야 한다.교육은 인간의 존엄과 가치를 존중하여야 한다.교육은 인간의 존엄과 가치를 존중하여야 한다."
  },
  {
    "id": "hrc-26-1",
    "name": "국가인권위원회법",
    "detail": "제26조(인권교육의 촉진)",
    "content": "위원회는 모든 사람의 인권의식을 깨우치고 향상시키기 위하여 필요한 인권교육과 홍보를 하여야 한다."
  },

  {
    "id": "edu-11",
    "name": "교육기본법",
    "detail": "제11조(인권존중)",
    "content": "교육은 인간의 존엄과 가치를 존중하여야 한다.교육은 인간의 존엄과 가치를 존중하여야 한다.교육은 인간의 존엄과 가치를 존중하여야 한다."
  },
  {
    "id": "hrc-26-1",
    "name": "국가인권위원회법",
    "detail": "제26조(인권교육의 촉진)",
    "content": "위원회는 모든 사람의 인권의식을 깨우치고 향상시키기 위하여 필요한 인권교육과 홍보를 하여야 한다."
  },

  {
    "id": "edu-11",
    "name": "교육기본법",
    "detail": "제11조(인권존중)",
    "content": "교육은 인간의 존엄과 가치를 존중하여야 한다.교육은 인간의 존엄과 가치를 존중하여야 한다.교육은 인간의 존엄과 가치를 존중하여야 한다."
  }
]
